<?xml version="1.0" encoding="UTF-8"?>
<!DOCTYPE plist PUBLIC "-//Apple//DTD PLIST 1.0//EN" "http://www.apple.com/DTDs/PropertyList-1.0.dtd">
<plist version="1.0">
<dict>
    <key>[em]不要[/em]</key>
	<string>comment_buyao</string>
	<key>[em]好[/em]</key>
	<string>comment_hao</string>
	<key>[em]爱你[/em]</key>
	<string>comment_aili</string>
	<key>[em]爱心[/em]</key>
	<string>comment_aixin</string>
	<key>[em]傲慢[/em]</key>
	<string>comment_aoman</string>
	<key>[em]白眼[/em]</key>
	<string>comment_baiyan</string>
	<key>[em]抱拳[/em]</key>
	<string>comment_baoquan</string>
	<key>[em]鄙视[/em]</key>
	<string>comment_bishi</string>
    <key>[em]闭嘴[/em]</key>
	<string>comment_bizhui</string>
    <key>[em]便便[/em]</key>
	<string>comment_bianbian</string>
    <key>[em]擦汗[/em]</key>
	<string>comment_chahan</string>
    <key>[em]菜刀[/em]</key>
	<string>comment_caidao</string>
    <key>[em]差劲[/em]</key>
	<string>comment_chajin</string>
    <key>[em]呲牙[/em]</key>
	<string>comment_ciya</string>
    <key>[em]大兵[/em]</key>
	<string>comment_dabing</string>
    <key>[em]大哭[/em]</key>
	<string>comment_daku</string>
    <key>[em]蛋糕[/em]</key>
	<string>comment_dangao</string>
    <key>[em]刀[/em]</key>
	<string>comment_dao</string>
    <key>[em]得意[/em]</key>
	<string>comment_deyi</string>
    <key>[em]凋谢[/em]</key>
	<string>comment_diaoxie</string>
    <key>[em]调皮[/em]</key>
	<string>comment_tiaopi</string>
    <key>[em]发呆[/em]</key>
	<string>comment_fadai</string>
    <key>[em]发怒[/em]</key>
	<string>comment_fanu</string>
    <key>[em]饭[/em]</key>
	<string>comment_fan</string>
    <key>[em]奋斗[/em]</key>
	<string>comment_fendou</string>
    <key>[em]尴尬[/em]</key>
	<string>comment_ganga</string>
    <key>[em]勾引[/em]</key>
	<string>comment_gouyin</string>
    <key>[em]鼓掌[/em]</key>
	<string>comment_guzhang</string>
    <key>[em]哈欠[/em]</key>
	<string>comment_haqian</string>
    <key>[em]害羞[/em]</key>
	<string>comment_haixiu</string>
    <key>[em]憨笑[/em]</key>
	<string>comment_hanxiao</string>
	<key>[em]坏笑[/em]</key>
	<string>comment_huaixiao</string>
    <key>[em]饥饿[/em]</key>
	<string>comment_jie</string>
    <key>[em]惊恐[/em]</key>
	<string>comment_jingkong</string>
    <key>[em]惊讶[/em]</key>
	<string>comment_jingya</string>
    <key>[em]咖啡[/em]</key>
	<string>comment_kafei</string>
    <key>[em]可爱[/em]</key>
	<string>comment_keai</string>
    <key>[em]可怜[/em]</key>
	<string>comment_kelian</string>
    <key>[em]抠鼻[/em]</key>
	<string>comment_koubi</string>
    <key>[em]骷髅[/em]</key>
	<string>comment_kulou</string>
    <key>[em]酷[/em]</key>
	<string>comment_ku</string>
    <key>[em]快哭了[/em]</key>
	<string>comment_kuaikule</string>
    <key>[em]左哼哼[/em]</key>
	<string>comment_zuohengheng</string>
    <key>[em]篮球[/em]</key>
	<string>comment_lanqiu</string>
    <key>[em]抓狂[/em]</key>
	<string>comment_zhuakuang</string>
    <key>[em]猪头[/em]</key>
	<string>comment_zhutou</string>
    <key>[em]咒骂[/em]</key>
	<string>comment_zhouma</string>
    <key>[em]折磨[/em]</key>
	<string>comment_zhemo</string>
    <key>[em]炸弹[/em]</key>
	<string>comment_zhadan</string>
    <key>[em]赞[/em]</key>
	<string>comment_zan</string>
    <key>[em]再见[/em]</key>
	<string>comment_zaijian</string>
    <key>[em]晕[/em]</key>
	<string>comment_yun</string>
    <key>[em]月亮[/em]</key>
	<string>comment_yueliang</string>
    <key>[em]右哼哼[/em]</key>
	<string>comment_youhengheng</string>
    <key>[em]拥抱[/em]</key>
	<string>comment_yongbao</string>
    <key>[em]阴险[/em]</key>
	<string>comment_yinxian</string>
    <key>[em]疑问[/em]</key>
	<string>comment_yiwen</string>
    <key>[em]嘘[/em]</key>
	<string>comment_xu</string>
    <key>[em]心碎了[/em]</key>
	<string>comment_xinsuile</string>
    <key>[em]吓[/em]</key>
	<string>comment_xia</string>
    <key>[em]西瓜[/em]</key>
	<string>comment_xigua</string>
    <key>[em]无语[/em]</key>
	<string>comment_wuyu</string>
    <key>[em]握手[/em]</key>
	<string>comment_woshou</string>
    <key>[em]委屈[/em]</key>
	<string>comment_weiqu</string>
    <key>[em]微笑[/em]</key>
	<string>comment_weixiao</string>
    <key>[em]吐[/em]</key>
	<string>comment_tu</string>
    <key>[em]偷笑[/em]</key>
	<string>comment_touxiao</string>
    <key>[em]太阳[/em]</key>
	<string>comment_taiyang</string>
    <key>[em]睡[/em]</key>
	<string>comment_shui</string>
    <key>[em]衰[/em]</key>
	<string>comment_shuai</string>
    <key>[em]示爱[/em]</key>
	<string>comment_shiai</string>
    <key>[em]胜利[/em]</key>
	<string>comment_shengli</string>
    <key>[em]闪电[/em]</key>
	<string>comment_shandian</string>
    <key>[em]色[/em]</key>
	<string>comment_se</string>
    <key>[em]弱[/em]</key>
	<string>comment_ruo</string>
    <key>[em]拳头[/em]</key>
	<string>comment_quantou</string>
    <key>[em]糗大了[/em]</key>
	<string>comment_qiudale</string>
    <key>[em]亲亲[/em]</key>
	<string>comment_qinqin</string>
    <key>[em]敲打[/em]</key>
	<string>comment_qiaoda</string>
    <key>[em]乒乓[/em]</key>
	<string>comment_pingpang</string>
    <key>[em]撇嘴[/em]</key>
	<string>comment_piezui</string>
    <key>[em]瓢虫[/em]</key>
	<string>comment_piaochong</string>
    <key>[em]啤酒[/em]</key>
	<string>comment_pijiu</string>
    <key>[em]难过[/em]</key>
	<string>comment_nanguo</string>
    <key>[em]玫瑰[/em]</key>
	<string>comment_meigui</string>
    <key>[em]流泪[/em]</key>
	<string>comment_liulei</string>
    <key>[em]礼物[/em]</key>
	<string>comment_liwu</string>
    <key>[em]冷汗[/em]</key>
	<string>comment_lenghan</string>
    <key>[em]足球[/em]</key>
	<string>comment_zuqiu</string>
    <key>[em]困[/em]</key>
	<string>comment_kun</string>
</dict>
</plist>
